ruamel.browser.client-0.2.10-py3.6-nspkg.pth
ruamel/browser/client/__init__.py
ruamel/browser/client/__main__.py
ruamel/browser/client/client.py
ruamel.browser.client-0.2.10.dist-info/DESCRIPTION.rst
ruamel.browser.client-0.2.10.dist-info/LICENSE.txt
ruamel.browser.client-0.2.10.dist-info/METADATA
ruamel.browser.client-0.2.10.dist-info/RECORD
ruamel.browser.client-0.2.10.dist-info/WHEEL
ruamel.browser.client-0.2.10.dist-info/entry_points.txt
ruamel.browser.client-0.2.10.dist-info/metadata.json
ruamel.browser.client-0.2.10.dist-info/namespace_packages.txt
ruamel.browser.client-0.2.10.dist-info/top_level.txt
